{
  "metadata": {
    "collected_at": "2026-01-08T19:21:58.971445Z",
    "record_count": 32
  },
  "data": [
    {
      "date": "2026-01-08",
      "wai_index": 28,
      "normalized_transaction_count": 1.0828,
      "normalized_volume": 0.407,
      "weight_tx": 0.0667,
      "weight_volume": 0.9333,
      "wai_index_v1": 34,
      "whale_tx_count": 17,
      "whale_tx_volume_btc": 7579.32,
      "sma_transaction_count": 15.7,
      "sma_volume": 18621.27
    },
    {
      "date": "2026-01-07",
      "wai_index": 97,
      "normalized_transaction_count": 1.1465,
      "normalized_volume": 2.2038,
      "weight_tx": 0.0667,
      "weight_volume": 0.9333,
      "wai_index_v1": 87,
      "whale_tx_count": 18,
      "whale_tx_volume_btc": 42429.8,
      "sma_transaction_count": 15.7,
      "sma_volume": 19252.89
    },
    {
      "date": "2026-01-06",
      "wai_index": 30,
      "normalized_transaction_count": 0.9677,
      "normalized_volume": 0.3917,
      "weight_tx": 0.1333,
      "weight_volume": 0.8667,
      "wai_index_v1": 30,
      "whale_tx_count": 15,
      "whale_tx_volume_btc": 7058.65,
      "sma_transaction_count": 15.5,
      "sma_volume": 18020.93
    },
    {
      "date": "2026-01-05",
      "wai_index": 52,
      "normalized_transaction_count": 1.0311,
      "normalized_volume": 1.0937,
      "weight_tx": 0.1034,
      "weight_volume": 0.8966,
      "wai_index_v1": 59,
      "whale_tx_count": 16,
      "whale_tx_volume_btc": 20122.02,
      "sma_transaction_count": 15.52,
      "sma_volume": 18398.94
    },
    {
      "date": "2026-01-04",
      "wai_index": 54,
      "normalized_transaction_count": 0.3871,
      "normalized_volume": 1.1746,
      "weight_tx": 0.0714,
      "weight_volume": 0.9286,
      "wai_index_v1": 39,
      "whale_tx_count": 6,
      "whale_tx_volume_btc": 21539.65,
      "sma_transaction_count": 15.5,
      "sma_volume": 18337.4
    },
    {
      "date": "2026-01-03",
      "wai_index": 22,
      "normalized_transaction_count": 0.5047,
      "normalized_volume": 0.2533,
      "weight_tx": 0.037,
      "weight_volume": 0.963,
      "wai_index_v1": 22,
      "whale_tx_count": 8,
      "whale_tx_volume_btc": 4614.88,
      "sma_transaction_count": 15.85,
      "sma_volume": 18218.8
    },
    {
      "date": "2026-01-02",
      "wai_index": 100,
      "normalized_transaction_count": 1.3,
      "normalized_volume": 4.088,
      "weight_tx": 0.0,
      "weight_volume": 1.0,
      "wai_index_v1": 100,
      "whale_tx_count": 21,
      "whale_tx_volume_btc": 76617.11,
      "sma_transaction_count": 16.15,
      "sma_volume": 18742.03
    },
    {
      "date": "2026-01-01",
      "wai_index": 56,
      "normalized_transaction_count": 0.5639,
      "normalized_volume": 1.4765,
      "weight_tx": 0.36,
      "weight_volume": 0.64,
      "wai_index_v1": 56,
      "whale_tx_count": 9,
      "whale_tx_volume_btc": 24254.13,
      "sma_transaction_count": 15.96,
      "sma_volume": 16427.03
    },
    {
      "date": "2025-12-31",
      "wai_index": 62,
      "normalized_transaction_count": 1.4154,
      "normalized_volume": 1.1084,
      "weight_tx": 0.2917,
      "weight_volume": 0.7083,
      "wai_index_v1": 58,
      "whale_tx_count": 23,
      "whale_tx_volume_btc": 17846.82,
      "sma_transaction_count": 16.25,
      "sma_volume": 16100.9
    },
    {
      "date": "2025-12-30",
      "wai_index": 26,
      "normalized_transaction_count": 0.6267,
      "normalized_volume": 0.3073,
      "weight_tx": 0.1304,
      "weight_volume": 0.8696,
      "wai_index_v1": 26,
      "whale_tx_count": 10,
      "whale_tx_volume_btc": 4923.95,
      "sma_transaction_count": 15.96,
      "sma_volume": 16024.99
    },
    {
      "date": "2025-12-29",
      "wai_index": 95,
      "normalized_transaction_count": 1.6639,
      "normalized_volume": 1.8836,
      "weight_tx": 0.0909,
      "weight_volume": 0.9091,
      "wai_index_v1": 95,
      "whale_tx_count": 27,
      "whale_tx_volume_btc": 31134.46,
      "sma_transaction_count": 16.23,
      "sma_volume": 16529.58
    },
    {
      "date": "2025-12-28",
      "wai_index": 19,
      "normalized_transaction_count": 0.2545,
      "normalized_volume": 0.1526,
      "weight_tx": 0.1905,
      "weight_volume": 0.8095,
      "wai_index_v1": 14,
      "whale_tx_count": 4,
      "whale_tx_volume_btc": 2416.47,
      "sma_transaction_count": 15.71,
      "sma_volume": 15834.11
    },
    {
      "date": "2025-12-27",
      "wai_index": 20,
      "normalized_transaction_count": 0.3067,
      "normalized_volume": 0.1595,
      "weight_tx": 0.2,
      "weight_volume": 0.8,
      "wai_index_v1": 15,
      "whale_tx_count": 5,
      "whale_tx_volume_btc": 2632.09,
      "sma_transaction_count": 16.3,
      "sma_volume": 16504.99
    },
    {
      "date": "2025-12-26",
      "wai_index": 21,
      "normalized_transaction_count": 0.6511,
      "normalized_volume": 0.2885,
      "weight_tx": 0.2105,
      "weight_volume": 0.7895,
      "wai_index_v1": 21,
      "whale_tx_count": 11,
      "whale_tx_volume_btc": 4972.75,
      "sma_transaction_count": 16.89,
      "sma_volume": 17235.15
    },
    {
      "date": "2025-12-25",
      "wai_index": 11,
      "normalized_transaction_count": 0.1161,
      "normalized_volume": 0.0382,
      "weight_tx": 0.2222,
      "weight_volume": 0.7778,
      "wai_index_v1": 6,
      "whale_tx_count": 2,
      "whale_tx_volume_btc": 683.76,
      "sma_transaction_count": 17.22,
      "sma_volume": 17916.39
    },
    {
      "date": "2025-12-24",
      "wai_index": 71,
      "normalized_transaction_count": 1.4351,
      "normalized_volume": 1.5423,
      "weight_tx": 0.4706,
      "weight_volume": 0.5294,
      "wai_index_v1": 82,
      "whale_tx_count": 26,
      "whale_tx_volume_btc": 29195.68,
      "sma_transaction_count": 18.12,
      "sma_volume": 18930.07
    },
    {
      "date": "2025-12-23",
      "wai_index": 81,
      "normalized_transaction_count": 1.2482,
      "normalized_volume": 2.0487,
      "weight_tx": 0.375,
      "weight_volume": 0.625,
      "wai_index_v1": 88,
      "whale_tx_count": 22,
      "whale_tx_volume_btc": 37467.36,
      "sma_transaction_count": 17.62,
      "sma_volume": 18288.47
    },
    {
      "date": "2025-12-22",
      "wai_index": 40,
      "normalized_transaction_count": 1.1538,
      "normalized_volume": 0.427,
      "weight_tx": 0.5333,
      "weight_volume": 0.4667,
      "wai_index_v1": 33,
      "whale_tx_count": 20,
      "whale_tx_volume_btc": 7263.45,
      "sma_transaction_count": 17.33,
      "sma_volume": 17009.88
    },
    {
      "date": "2025-12-21",
      "wai_index": 71,
      "normalized_transaction_count": 1.4583,
      "normalized_volume": 1.5086,
      "weight_tx": 0.5714,
      "weight_volume": 0.4286,
      "wai_index_v1": 86,
      "whale_tx_count": 25,
      "whale_tx_volume_btc": 26710.84,
      "sma_transaction_count": 17.14,
      "sma_volume": 17706.05
    },
    {
      "date": "2025-12-20",
      "wai_index": 31,
      "normalized_transaction_count": 0.2419,
      "normalized_volume": 1.2402,
      "weight_tx": 0.5385,
      "weight_volume": 0.4615,
      "wai_index_v1": 23,
      "whale_tx_count": 4,
      "whale_tx_volume_btc": 21100.82,
      "sma_transaction_count": 16.54,
      "sma_volume": 17013.38
    },
    {
      "date": "2025-12-19",
      "wai_index": 92,
      "normalized_transaction_count": 1.9336,
      "normalized_volume": 1.7293,
      "weight_tx": 0.4167,
      "weight_volume": 0.5833,
      "wai_index_v1": 100,
      "whale_tx_count": 34,
      "whale_tx_volume_btc": 28832.04,
      "sma_transaction_count": 17.58,
      "sma_volume": 16672.76
    },
    {
      "date": "2025-12-18",
      "wai_index": 36,
      "normalized_transaction_count": 1.1808,
      "normalized_volume": 0.505,
      "weight_tx": 0.4545,
      "weight_volume": 0.5455,
      "wai_index_v1": 36,
      "whale_tx_count": 19,
      "whale_tx_volume_btc": 7861.76,
      "sma_transaction_count": 16.09,
      "sma_volume": 15567.37
    },
    {
      "date": "2025-12-17",
      "wai_index": 60,
      "normalized_transaction_count": 1.7722,
      "normalized_volume": 0.799,
      "weight_tx": 0.4,
      "weight_volume": 0.6,
      "wai_index_v1": 60,
      "whale_tx_count": 28,
      "whale_tx_volume_btc": 13053.39,
      "sma_transaction_count": 15.8,
      "sma_volume": 16337.93
    },
    {
      "date": "2025-12-16",
      "wai_index": 56,
      "normalized_transaction_count": 0.9,
      "normalized_volume": 1.1259,
      "weight_tx": 0.2222,
      "weight_volume": 0.7778,
      "wai_index_v1": 56,
      "whale_tx_count": 13,
      "whale_tx_volume_btc": 18806.32,
      "sma_transaction_count": 14.44,
      "sma_volume": 16702.88
    },
    {
      "date": "2025-12-15",
      "wai_index": 88,
      "normalized_transaction_count": 1.641,
      "normalized_volume": 1.7922,
      "weight_tx": 0.0,
      "weight_volume": 1.0,
      "wai_index_v1": 100,
      "whale_tx_count": 24,
      "whale_tx_volume_btc": 29463.02,
      "sma_transaction_count": 14.62,
      "sma_volume": 16439.95
    },
    {
      "date": "2025-12-14",
      "wai_index": 29,
      "normalized_transaction_count": 0.3763,
      "normalized_volume": 0.0992,
      "weight_tx": 0.0,
      "weight_volume": 1.0,
      "wai_index_v1": 29,
      "whale_tx_count": 5,
      "whale_tx_volume_btc": 1446.11,
      "sma_transaction_count": 13.29,
      "sma_volume": 14579.51
    },
    {
      "date": "2025-12-13",
      "wai_index": 17,
      "normalized_transaction_count": 0.1364,
      "normalized_volume": 0.027,
      "weight_tx": 0.0,
      "weight_volume": 1.0,
      "wai_index_v1": 17,
      "whale_tx_count": 2,
      "whale_tx_volume_btc": 451.99,
      "sma_transaction_count": 14.67,
      "sma_volume": 16768.41
    },
    {
      "date": "2025-12-12",
      "wai_index": 100,
      "normalized_transaction_count": 0.7558,
      "normalized_volume": 1.8948,
      "weight_tx": 0.0,
      "weight_volume": 1.0,
      "wai_index_v1": 80,
      "whale_tx_count": 13,
      "whale_tx_volume_btc": 37955.07,
      "sma_transaction_count": 17.2,
      "sma_volume": 20031.69
    },
    {
      "date": "2025-12-11",
      "wai_index": 25,
      "normalized_transaction_count": 0.9863,
      "normalized_volume": 0.5567,
      "weight_tx": 0.25,
      "weight_volume": 0.75,
      "wai_index_v1": 25,
      "whale_tx_count": 18,
      "whale_tx_volume_btc": 8657.06,
      "sma_transaction_count": 18.25,
      "sma_volume": 15550.85
    },
    {
      "date": "2025-12-10",
      "wai_index": 67,
      "normalized_transaction_count": 1.4182,
      "normalized_volume": 1.2072,
      "weight_tx": 0.3333,
      "weight_volume": 0.6667,
      "wai_index_v1": 67,
      "whale_tx_count": 26,
      "whale_tx_volume_btc": 21547.28,
      "sma_transaction_count": 18.33,
      "sma_volume": 17848.78
    },
    {
      "date": "2025-12-09",
      "wai_index": 100,
      "normalized_transaction_count": 1.1724,
      "normalized_volume": 1.6581,
      "weight_tx": 0.0,
      "weight_volume": 1.0,
      "wai_index_v1": 100,
      "whale_tx_count": 17,
      "whale_tx_volume_btc": 26528.09,
      "sma_transaction_count": 14.5,
      "sma_volume": 15999.53
    },
    {
      "date": "2025-12-08",
      "wai_index": 100,
      "normalized_transaction_count": 1.0,
      "normalized_volume": 1.0,
      "weight_tx": 0.0,
      "weight_volume": 1.0,
      "wai_index_v1": 100,
      "whale_tx_count": 12,
      "whale_tx_volume_btc": 5470.97,
      "sma_transaction_count": 12.0,
      "sma_volume": 5470.97
    }
  ]
}