{
  "metadata": {
    "collected_at": "2026-01-10T18:30:19.343659Z",
    "record_count": 33
  },
  "data": [
    {
      "date": "2026-01-10",
      "wai_index": 18,
      "normalized_transaction_count": 0.3956,
      "normalized_volume": 0.2237,
      "weight_tx": 0.1,
      "weight_volume": 0.9,
      "wai_index_v1": 18,
      "whale_tx_count": 6,
      "whale_tx_volume_btc": 4164.5,
      "sma_transaction_count": 15.17,
      "sma_volume": 18619.87
    },
    {
      "date": "2026-01-09",
      "wai_index": 62,
      "normalized_transaction_count": 1.1563,
      "normalized_volume": 1.257,
      "weight_tx": 0.2,
      "weight_volume": 0.8,
      "wai_index_v1": 62,
      "whale_tx_count": 18,
      "whale_tx_volume_btc": 23594.01,
      "sma_transaction_count": 15.57,
      "sma_volume": 18769.62
    },
    {
      "date": "2026-01-08",
      "wai_index": 32,
      "normalized_transaction_count": 1.3263,
      "normalized_volume": 0.5338,
      "weight_tx": 0.1,
      "weight_volume": 0.9,
      "wai_index_v1": 45,
      "whale_tx_count": 21,
      "whale_tx_volume_btc": 9983.22,
      "sma_transaction_count": 15.83,
      "sma_volume": 18701.4
    },
    {
      "date": "2026-01-07",
      "wai_index": 93,
      "normalized_transaction_count": 1.1868,
      "normalized_volume": 2.3076,
      "weight_tx": 0.1,
      "weight_volume": 0.9,
      "wai_index_v1": 83,
      "whale_tx_count": 18,
      "whale_tx_volume_btc": 42429.8,
      "sma_transaction_count": 15.17,
      "sma_volume": 18386.97
    },
    {
      "date": "2026-01-06",
      "wai_index": 31,
      "normalized_transaction_count": 0.9954,
      "normalized_volume": 0.402,
      "weight_tx": 0.1379,
      "weight_volume": 0.8621,
      "wai_index_v1": 31,
      "whale_tx_count": 15,
      "whale_tx_volume_btc": 7058.65,
      "sma_transaction_count": 15.07,
      "sma_volume": 17557.9
    },
    {
      "date": "2026-01-05",
      "wai_index": 54,
      "normalized_transaction_count": 1.0616,
      "normalized_volume": 1.1221,
      "weight_tx": 0.1071,
      "weight_volume": 0.8929,
      "wai_index_v1": 57,
      "whale_tx_count": 16,
      "whale_tx_volume_btc": 20122.02,
      "sma_transaction_count": 15.07,
      "sma_volume": 17932.88
    },
    {
      "date": "2026-01-04",
      "wai_index": 56,
      "normalized_transaction_count": 0.399,
      "normalized_volume": 1.2066,
      "weight_tx": 0.0741,
      "weight_volume": 0.9259,
      "wai_index_v1": 37,
      "whale_tx_count": 6,
      "whale_tx_volume_btc": 21539.65,
      "sma_transaction_count": 15.04,
      "sma_volume": 17851.8
    },
    {
      "date": "2026-01-03",
      "wai_index": 23,
      "normalized_transaction_count": 0.52,
      "normalized_volume": 0.2606,
      "weight_tx": 0.0385,
      "weight_volume": 0.9615,
      "wai_index_v1": 23,
      "whale_tx_count": 8,
      "whale_tx_volume_btc": 4614.88,
      "sma_transaction_count": 15.38,
      "sma_volume": 17709.96
    },
    {
      "date": "2026-01-02",
      "wai_index": 100,
      "normalized_transaction_count": 1.3393,
      "normalized_volume": 4.2019,
      "weight_tx": 0.0,
      "weight_volume": 1.0,
      "wai_index_v1": 100,
      "whale_tx_count": 21,
      "whale_tx_volume_btc": 76617.11,
      "sma_transaction_count": 15.68,
      "sma_volume": 18233.76
    },
    {
      "date": "2026-01-01",
      "wai_index": 54,
      "normalized_transaction_count": 0.5822,
      "normalized_volume": 1.535,
      "weight_tx": 0.5417,
      "weight_volume": 0.4583,
      "wai_index_v1": 54,
      "whale_tx_count": 9,
      "whale_tx_volume_btc": 24254.13,
      "sma_transaction_count": 15.46,
      "sma_volume": 15801.12
    },
    {
      "date": "2025-12-31",
      "wai_index": 61,
      "normalized_transaction_count": 1.4613,
      "normalized_volume": 1.1564,
      "weight_tx": 0.4783,
      "weight_volume": 0.5217,
      "wai_index_v1": 61,
      "whale_tx_count": 23,
      "whale_tx_volume_btc": 17846.82,
      "sma_transaction_count": 15.74,
      "sma_volume": 15433.6
    },
    {
      "date": "2025-12-30",
      "wai_index": 27,
      "normalized_transaction_count": 0.649,
      "normalized_volume": 0.3213,
      "weight_tx": 0.2727,
      "weight_volume": 0.7273,
      "wai_index_v1": 27,
      "whale_tx_count": 10,
      "whale_tx_volume_btc": 4923.95,
      "sma_transaction_count": 15.41,
      "sma_volume": 15323.9
    },
    {
      "date": "2025-12-29",
      "wai_index": 81,
      "normalized_transaction_count": 1.7234,
      "normalized_volume": 1.9682,
      "weight_tx": 0.2381,
      "weight_volume": 0.7619,
      "wai_index_v1": 86,
      "whale_tx_count": 27,
      "whale_tx_volume_btc": 31134.46,
      "sma_transaction_count": 15.67,
      "sma_volume": 15819.14
    },
    {
      "date": "2025-12-28",
      "wai_index": 20,
      "normalized_transaction_count": 0.2649,
      "normalized_volume": 0.1605,
      "weight_tx": 0.25,
      "weight_volume": 0.75,
      "wai_index_v1": 15,
      "whale_tx_count": 4,
      "whale_tx_volume_btc": 2416.47,
      "sma_transaction_count": 15.1,
      "sma_volume": 15053.37
    },
    {
      "date": "2025-12-27",
      "wai_index": 21,
      "normalized_transaction_count": 0.3188,
      "normalized_volume": 0.1675,
      "weight_tx": 0.3684,
      "weight_volume": 0.6316,
      "wai_index_v1": 16,
      "whale_tx_count": 5,
      "whale_tx_volume_btc": 2632.09,
      "sma_transaction_count": 15.68,
      "sma_volume": 15718.47
    },
    {
      "date": "2025-12-26",
      "wai_index": 22,
      "normalized_transaction_count": 0.6758,
      "normalized_volume": 0.3024,
      "weight_tx": 0.3889,
      "weight_volume": 0.6111,
      "wai_index_v1": 22,
      "whale_tx_count": 11,
      "whale_tx_volume_btc": 4972.75,
      "sma_transaction_count": 16.28,
      "sma_volume": 16445.5
    },
    {
      "date": "2025-12-25",
      "wai_index": 12,
      "normalized_transaction_count": 0.1206,
      "normalized_volume": 0.0399,
      "weight_tx": 0.4118,
      "weight_volume": 0.5882,
      "wai_index_v1": 6,
      "whale_tx_count": 2,
      "whale_tx_volume_btc": 683.76,
      "sma_transaction_count": 16.59,
      "sma_volume": 17120.36
    },
    {
      "date": "2025-12-24",
      "wai_index": 62,
      "normalized_transaction_count": 1.4857,
      "normalized_volume": 1.6088,
      "weight_tx": 0.5625,
      "weight_volume": 0.4375,
      "wai_index_v1": 62,
      "whale_tx_count": 26,
      "whale_tx_volume_btc": 29195.68,
      "sma_transaction_count": 17.5,
      "sma_volume": 18147.65
    },
    {
      "date": "2025-12-23",
      "wai_index": 73,
      "normalized_transaction_count": 1.2992,
      "normalized_volume": 2.1519,
      "weight_tx": 0.5333,
      "weight_volume": 0.4667,
      "wai_index_v1": 80,
      "whale_tx_count": 22,
      "whale_tx_volume_btc": 37467.36,
      "sma_transaction_count": 16.93,
      "sma_volume": 17411.12
    },
    {
      "date": "2025-12-22",
      "wai_index": 29,
      "normalized_transaction_count": 1.2069,
      "normalized_volume": 0.4546,
      "weight_tx": 0.5714,
      "weight_volume": 0.4286,
      "wai_index_v1": 29,
      "whale_tx_count": 20,
      "whale_tx_volume_btc": 7263.45,
      "sma_transaction_count": 16.57,
      "sma_volume": 15978.53
    },
    {
      "date": "2025-12-21",
      "wai_index": 69,
      "normalized_transaction_count": 1.533,
      "normalized_volume": 1.6044,
      "weight_tx": 0.6154,
      "weight_volume": 0.3846,
      "wai_index_v1": 77,
      "whale_tx_count": 25,
      "whale_tx_volume_btc": 26710.84,
      "sma_transaction_count": 16.31,
      "sma_volume": 16648.92
    },
    {
      "date": "2025-12-20",
      "wai_index": 25,
      "normalized_transaction_count": 0.2567,
      "normalized_volume": 1.3346,
      "weight_tx": 0.5833,
      "weight_volume": 0.4167,
      "wai_index_v1": 25,
      "whale_tx_count": 4,
      "whale_tx_volume_btc": 21100.82,
      "sma_transaction_count": 15.58,
      "sma_volume": 15810.42
    },
    {
      "date": "2025-12-19",
      "wai_index": 82,
      "normalized_transaction_count": 2.0437,
      "normalized_volume": 1.8808,
      "weight_tx": 0.5455,
      "weight_volume": 0.4545,
      "wai_index_v1": 91,
      "whale_tx_count": 34,
      "whale_tx_volume_btc": 28832.04,
      "sma_transaction_count": 16.64,
      "sma_volume": 15329.48
    },
    {
      "date": "2025-12-18",
      "wai_index": 30,
      "normalized_transaction_count": 1.2752,
      "normalized_volume": 0.5624,
      "weight_tx": 0.5,
      "weight_volume": 0.5,
      "wai_index_v1": 30,
      "whale_tx_count": 19,
      "whale_tx_volume_btc": 7861.76,
      "sma_transaction_count": 14.9,
      "sma_volume": 13979.22
    },
    {
      "date": "2025-12-17",
      "wai_index": 67,
      "normalized_transaction_count": 1.9385,
      "normalized_volume": 0.8905,
      "weight_tx": 0.4444,
      "weight_volume": 0.5556,
      "wai_index_v1": 67,
      "whale_tx_count": 28,
      "whale_tx_volume_btc": 13053.39,
      "sma_transaction_count": 14.44,
      "sma_volume": 14658.94
    },
    {
      "date": "2025-12-16",
      "wai_index": 62,
      "normalized_transaction_count": 1.0196,
      "normalized_volume": 1.2656,
      "weight_tx": 0.375,
      "weight_volume": 0.625,
      "wai_index_v1": 62,
      "whale_tx_count": 13,
      "whale_tx_volume_btc": 18806.32,
      "sma_transaction_count": 12.75,
      "sma_volume": 14859.64
    },
    {
      "date": "2025-12-15",
      "wai_index": 86,
      "normalized_transaction_count": 1.8876,
      "normalized_volume": 2.061,
      "weight_tx": 0.0,
      "weight_volume": 1.0,
      "wai_index_v1": 100,
      "whale_tx_count": 24,
      "whale_tx_volume_btc": 29463.02,
      "sma_transaction_count": 12.71,
      "sma_volume": 14295.82
    },
    {
      "date": "2025-12-14",
      "wai_index": 33,
      "normalized_transaction_count": 0.4615,
      "normalized_volume": 0.1229,
      "weight_tx": 0.0,
      "weight_volume": 1.0,
      "wai_index_v1": 33,
      "whale_tx_count": 5,
      "whale_tx_volume_btc": 1446.11,
      "sma_transaction_count": 10.83,
      "sma_volume": 11767.96
    },
    {
      "date": "2025-12-13",
      "wai_index": 20,
      "normalized_transaction_count": 0.1667,
      "normalized_volume": 0.0327,
      "weight_tx": 0.0,
      "weight_volume": 1.0,
      "wai_index_v1": 20,
      "whale_tx_count": 2,
      "whale_tx_volume_btc": 451.99,
      "sma_transaction_count": 12.0,
      "sma_volume": 13832.33
    },
    {
      "date": "2025-12-12",
      "wai_index": 100,
      "normalized_transaction_count": 0.8966,
      "normalized_volume": 2.2096,
      "weight_tx": 0.0,
      "weight_volume": 1.0,
      "wai_index_v1": 75,
      "whale_tx_count": 13,
      "whale_tx_volume_btc": 37955.07,
      "sma_transaction_count": 14.5,
      "sma_volume": 17177.41
    },
    {
      "date": "2025-12-11",
      "wai_index": 33,
      "normalized_transaction_count": 1.2,
      "normalized_volume": 0.8445,
      "weight_tx": 0.3333,
      "weight_volume": 0.6667,
      "wai_index_v1": 67,
      "whale_tx_count": 18,
      "whale_tx_volume_btc": 8657.06,
      "sma_transaction_count": 15.0,
      "sma_volume": 10251.52
    },
    {
      "date": "2025-12-10",
      "wai_index": 100,
      "normalized_transaction_count": 1.9259,
      "normalized_volume": 1.9502,
      "weight_tx": 0.0,
      "weight_volume": 1.0,
      "wai_index_v1": 100,
      "whale_tx_count": 26,
      "whale_tx_volume_btc": 21547.28,
      "sma_transaction_count": 13.5,
      "sma_volume": 11048.75
    },
    {
      "date": "2025-12-09",
      "wai_index": 100,
      "normalized_transaction_count": 1.0,
      "normalized_volume": 1.0,
      "weight_tx": 0.0,
      "weight_volume": 1.0,
      "wai_index_v1": 100,
      "whale_tx_count": 1,
      "whale_tx_volume_btc": 550.23,
      "sma_transaction_count": 1.0,
      "sma_volume": 550.23
    }
  ]
}